[{"aid": 116119692252941, "videos": 4, "tid": 172, "tname": "手机游戏", "copyright": 1, "pic": "http://i2.hdslb.com/bfs/archive/e5958fcab43bcaefdcc77d787b34f15f370ec70f.jpg", "title": "《原神》角色预告-「法尔伽：骑士精神」", "pubdate": 1771905600, "ctime": 1771846203, "desc": "是骑士精神决定了他应该有的样子，还是成为骑士的人决定这个身份应当有的面貌？\n法尔伽应该不会花费太多时间思考这个问题，自由的风总是不停歇，他的随心所欲也是。\n \n中文CV：\n法尔伽——郝祥海\n可莉——花玲\n米卡——邓宥希\n琴——林簌\n迪奥娜——诺亚\n诺艾尔——宴宁\n雷泽——周帅\n菲谢尔——Mace\n温迪——喵酱\n \n日文CV：\n法尔伽——杉田智和\n可莉——久野美咲\n米卡——三瓶由布子\n琴——斋藤千和\n迪奥娜——井泽诗织\n诺艾尔——高尾奏音\n雷泽——内山昂辉\n菲谢尔——内田真礼\n温迪——村濑步\n\n《原神》bi", "state": 0, "duration": 786, "rights": {"bp": 0, "elec": 0, "download": 0, "movie": 0, "pay": 0, "hd5": 1, "no_reprint": 1, "autoplay": 1, "ugc_pay": 0, "is_cooperation": 0, "ugc_pay_preview": 0, "no_background": 0, "arc_pay": 0, "pay_free_watch": 0}, "owner": {"mid": 401742377, "name": "原神", "face": "https://i2.hdslb.com/bfs/face/853c4a846793dfbdafd8f16a40d6d8065bdb7c6f.jpg"}, "stat": {"aid": 116119692252941, "view": 2264189, "danmaku": 12888, "reply": 14799, "favorite": 48878, "coin": 94976, "share": 29727, "now_rank": 0, "his_rank": 3, "like": 265808, "dislike": 0, "vt": 0, "vv": 2264189, "fav_g": 1848, "like_g": 1203}, "dynamic": "#原神# #法尔伽# #骑士精神# \n《原神》角色预告-「法尔伽：骑士精神」", "cid": 36235251286, "dimension": {"width": 1920, "height": 1080, "rotate": 0}, "short_link_v2": "https://b23.tv/BV1VrfiBMEsQ", "first_frame": "http://i2.hdslb.com/bfs/storyff/_000011j1bvgcxe5ig2pgootsmytd8bb_firsti.jpg", "pub_location": "上海", "cover43": "http://i2.hdslb.com/bfs/archive/c386684076f9d6df05f143c1f04dd9b9e3a4cda2.jpg", "tidv2": 2064, "tnamev2": "单人RPG游戏", "pid_v2": 1008, "pid_name_v2": "游戏", "bvid": "BV1VrfiBMEsQ", "season_type": 0, "is_ogv": false, "ogv_info": null, "enable_vt": 0, "ai_rcmd": null, "rcmd_reason": {"content": "百万播放", "corner_mark": 0}}, {"aid": 116123836154344, "videos": 1, "tid": 22, "tname": "鬼畜调教", "copyright": 1, "pic": "http://i1.hdslb.com/bfs/archive/dc1f1167da54a077e9458f214759d217e7e03c4c.jpg", "title": "⚡ 纯情干员火辣辣 ⚡", "pubdate": 1771909804, "ctime": 1771909441, "desc": "", "state": 0, "duration": 129, "mission_id": 4058133, "rights": {"bp": 0, "elec": 0, "download": 0, "movie": 0, "pay": 0, "hd5": 1, "no_reprint": 1, "autoplay": 1, "ugc_pay": 0, "is_cooperation": 1, "ugc_pay_preview": 0, "no_background": 0, "arc_pay": 0, "pay_free_watch": 0}, "owner": {"mid": 59905809, "name": "哦呼w", "face": "https://i0.hdslb.com/bfs/face/57ead5621801ec8a637bc47754e00e9ae6e62888.gif"}, "stat": {"aid": 116123836154344, "view": 569122, "danmaku": 354, "reply": 614, "favorite": 7077, "coin": 3114, "share": 712, "now_rank": 0, "his_rank": 0, "like": 27995, "dislike": 0, "vt": 0, "vv": 569122, "fav_g": 2, "like_g": 0}, "dynamic": "", "cid": 36248292880, "dimension": {"width": 1920, "height": 1080, "rotate": 0}, "short_link_v2": "https://b23.tv/BV1mAfCBjEF3", "first_frame": "http://i1.hdslb.com/bfs/storyff/_00003aow0ff1z8bt922b2f3dk4f1zeb_firsti.jpg", "pub_location": "湖北", "cover43": "http://i1.hdslb.com/bfs/archive/a41dbe00501ff7e5cc59271fa6233b7ec72277a2.jpg", "tidv2": 2063, "tnamev2": "鬼畜综合", "pid_v2": 1007, "pid_name_v2": "鬼畜", "bvid": "BV1mAfCBjEF3", "season_type": 0, "is_ogv": false, "ogv_info": null, "enable_vt": 0, "ai_rcmd": null, "rcmd_reason": {"content": "", "corner_mark": 0}}, {"aid": 116118517712441, "videos": 1, "tid": 138, "tname": "搞笑", "copyright": 1, "pic": "http://i2.hdslb.com/bfs/archive/17a86bde2cd08e1a98f2bed25cfbe8ff74befe23.jpg", "title": "老师嘲讽学生摔倒结果老师摔倒100次！！", "pubdate": 1771831800, "ctime": 1771828102, "desc": "", "state": 0, "duration": 118, "mission_id": 4057995, "rights": {"bp": 0, "elec": 0, "download": 0, "movie": 0, "pay": 0, "hd5": 1, "no_reprint": 1, "autoplay": 1, "ugc_pay": 0, "is_cooperation": 0, "ugc_pay_preview": 0, "no_background": 0, "arc_pay": 0, "pay_free_watch": 0}, "owner": {"mid": 3546921513782109, "name": "我是七奇", "face": "https://i0.hdslb.com/bfs/face/a5e690d4927edc7f98bdb374d7e8f0dde93e4c82.jpg"}, "stat": {"aid": 116118517712441, "view": 5600910, "danmaku": 476, "reply": 2053, "favorite": 28124, "coin": 2970, "share": 4651, "now_rank": 0, "his_rank": 36, "like": 161753, "dislike": 0, "vt": 0, "vv": 5600910, "fav_g": 12142, "like_g": 7997}, "dynamic": "", "cid": 36229680861, "dimension": {"width": 1920, "height": 1080, "rotate": 0}, "short_link_v2": "https://b23.tv/BV1PCfTBVEQd", "first_frame": "http://i0.hdslb.com/bfs/storyff/_00002bgka63msyz512uz56h2m2wt6ib_firsti.jpg", "pub_location": "广东", "cover43": "http://i1.hdslb.com/bfs/archive/52fefc5f0aa4288544ccfc25c3a3a125f0d3d328.jpg", "tidv2": 2154, "tnamev2": "剧情演绎", "pid_v2": 1021, "pid_name_v2": "小剧场", "bvid": "BV1PCfTBVEQd", "season_type": 0, "is_ogv": false, "ogv_info": null, "enable_vt": 0, "ai_rcmd": null, "rcmd_reason": {"content": "百万播放", "corner_mark": 1}}, {"aid": 116124003868261, "videos": 1, "tid": 71, "tname": "综艺", "copyright": 1, "pic": "http://i0.hdslb.com/bfs/archive/e75fdfdfbea845ba4b4031bf16dbc474568ca279.jpg", "title": "冰 天 雪 地 好 朋 友 ！【青春旅行团13】", "pubdate": 1771923600, "ctime": 1771912738, "desc": "全！新！系！列！！《青春旅行团》第二季,第七期！！ 随机一个人策划一期旅游，这次是冰冻篇！！ 喜欢的话请多多一键三连吧！！", "state": 0, "duration": 2580, "rights": {"bp": 0, "elec": 0, "download": 0, "movie": 0, "pay": 0, "hd5": 0, "no_reprint": 1, "autoplay": 1, "ugc_pay": 0, "is_cooperation": 1, "ugc_pay_preview": 0, "no_background": 0, "arc_pay": 0, "pay_free_watch": 0}, "owner": {"mid": 10897366, "name": "小精灵real", "face": "https://i1.hdslb.com/bfs/face/a133623b0165a75893bfe2a1f458a183c6c68fe1.jpg"}, "stat": {"aid": 116124003868261, "view": 750064, "danmaku": 32896, "reply": 5073, "favorite": 33928, "coin": 91205, "share": 6360, "now_rank": 0, "his_rank": 11, "like": 109317, "dislike": 0, "vt": 0, "vv": 750064, "fav_g": 138, "like_g": 6}, "dynamic": "", "cid": 36249338153, "dimension": {"width": 3840, "height": 2160, "rotate": 0}, "short_link_v2": "https://b23.tv/BV1JEfCBKE1g", "first_frame": "http://i0.hdslb.com/bfs/storyff/_00003qcwh13tr4mpt256741dpxpnscb_firsti.jpg", "pub_location": "新疆", "cover43": "http://i1.hdslb.com/bfs/archive/2f8c588ed3e75e2a647637486fd123c23bd63509.jpg", "tidv2": 2207, "tnamev2": "随拍·综合", "pid_v2": 1032, "pid_name_v2": "其他", "bvid": "BV1JEfCBKE1g", "season_type": 0, "is_ogv": false, "ogv_info": null, "enable_vt": 0, "ai_rcmd": null, "rcmd_reason": {"content": "10万点赞", "corner_mark": 1}}, {"aid": 116114575072948, "videos": 1, "tid": 76, "tname": "美食制作", "copyright": 1, "pic": "http://i1.hdslb.com/bfs/archive/830837bf5150fa6cf58a20519b204842674edf9d.jpg", "title": "13个年糕的终极爆改吃法～有手就会系列", "pubdate": 1771898400, "ctime": 1771768057, "desc": "", "state": 0, "duration": 396, "mission_id": 4058762, "rights": {"bp": 0, "elec": 0, "download": 0, "movie": 0, "pay": 0, "hd5": 1, "no_reprint": 1, "autoplay": 1, "ugc_pay": 0, "is_cooperation": 0, "ugc_pay_preview": 0, "no_background": 0, "arc_pay": 0, "pay_free_watch": 0}, "owner": {"mid": 17495873, "name": "胡仔一人食", "face": "http://i2.hdslb.com/bfs/face/a8b58959ad0ab6186e284b824c9f5ddfc5512fdb.jpg"}, "stat": {"aid": 116114575072948, "view": 1311295, "danmaku": 449, "reply": 764, "favorite": 16915, "coin": 1412, "share": 3139, "now_rank": 0, "his_rank": 81, "like": 55168, "dislike": 0, "vt": 0, "vv": 1311295, "fav_g": 69, "like_g": 43}, "dynamic": "", "cid": 36218146733, "dimension": {"width": 1080, "height": 1920, "rotate": 0}, "short_link_v2": "https://b23.tv/BV12VfPBKEDc", "first_frame": "http://i0.hdslb.com/bfs/storyff/_00001dg3i9tqavbi920y47ix00ncj1b_firsti.jpg", "pub_location": "河南", "cover43": "http://i0.hdslb.com/bfs/archive/9e0415e89cc4d15d998290af9ce0979d7762cd9f.jpg", "tidv2": 2149, "tnamev2": "美食制作", "pid_v2": 1020, "pid_name_v2": "美食", "bvid": "BV12VfPBKEDc", "season_type": 0, "is_ogv": false, "ogv_info": null, "enable_vt": 0, "ai_rcmd": null, "rcmd_reason": {"content": "百万播放", "corner_mark": 1}}, {"aid": 116123181784747, "videos": 1, "tid": 216, "tname": "鬼畜剧场", "copyright": 1, "pic": "http://i1.hdslb.com/bfs/archive/7a6ecf33e49f0a85bcf98ffcf30167665ea2d675.jpg", "title": "coke和雨妹", "pubdate": 1771899405, "ctime": 1771899405, "desc": "-", "state": 0, "duration": 228, "rights": {"bp": 0, "elec": 0, "download": 0, "movie": 0, "pay": 0, "hd5": 0, "no_reprint": 1, "autoplay": 1, "ugc_pay": 0, "is_cooperation": 0, "ugc_pay_preview": 0, "no_background": 0, "arc_pay": 0, "pay_free_watch": 0}, "owner": {"mid": 3546653359343881, "name": "无敌熊大帝", "face": "https://i1.hdslb.com/bfs/face/6d05fb6b40ecba5e7442caf828794aab3f978bf5.jpg"}, "stat": {"aid": 116123181784747, "view": 654822, "danmaku": 589, "reply": 1448, "favorite": 6172, "coin": 1000, "share": 8987, "now_rank": 0, "his_rank": 0, "like": 44569, "dislike": 0, "vt": 0, "vv": 654822, "fav_g": 0, "like_g": 0}, "dynamic": "", "cid": 36245866209, "dimension": {"width": 1920, "height": 1080, "rotate": 0}, "short_link_v2": "https://b23.tv/BV124fyBUEsn", "up_from_v2": 35, "first_frame": "http://i0.hdslb.com/bfs/storyff/_00000k7wkel69xo5g2qfhje6vbdq42b_firsti.jpg", "pub_location": "河南", "cover43": "http://i0.hdslb.com/bfs/archive/94e706907eaafd91eefd9f63028d3e8d2eca5ab7.jpg", "tidv2": 2002, "tnamev2": "影视剪辑", "pid_v2": 1001, "pid_name_v2": "影视", "bvid": "BV124fyBUEsn", "season_type": 0, "is_ogv": false, "ogv_info": null, "enable_vt": 0, "ai_rcmd": null, "rcmd_reason": {"content": "", "corner_mark": 0}}, {"aid": 116124658311092, "videos": 1, "tid": 85, "tname": "小剧场", "copyright": 1, "pic": "http://i0.hdslb.com/bfs/archive/3d573ee68a194de5de8be4f16c3f4a4ce05069db.jpg", "title": "过年和爸妈一起旅游be like！下次真的不敢了！！", "pubdate": 1771929600, "ctime": 1771922399, "desc": "-", "state": 0, "duration": 137, "rights": {"bp": 0, "elec": 0, "download": 0, "movie": 0, "pay": 0, "hd5": 0, "no_reprint": 1, "autoplay": 1, "ugc_pay": 0, "is_cooperation": 0, "ugc_pay_preview": 0, "no_background": 0, "arc_pay": 0, "pay_free_watch": 0}, "owner": {"mid": 474853499, "name": "李如儒也是李蠕蠕", "face": "https://i2.hdslb.com/bfs/face/8da8eac46ef637b771efeabf4b7b4b093d34dea5.jpg"}, "stat": {"aid": 116124658311092, "view": 519250, "danmaku": 238, "reply": 441, "favorite": 919, "coin": 840, "share": 661, "now_rank": 0, "his_rank": 0, "like": 26525, "dislike": 0, "vt": 0, "vv": 519250, "fav_g": 17, "like_g": 25}, "dynamic": "", "cid": 36253470308, "dimension": {"width": 2160, "height": 3840, "rotate": 0}, "short_link_v2": "https://b23.tv/BV1uPf1BsEGX", "up_from_v2": 36, "first_frame": "http://i0.hdslb.com/bfs/storyff/_000039wca0z60msm72uyfrjxjch38tb_firsti.jpg", "pub_location": "吉林", "cover43": "http://i1.hdslb.com/bfs/archive/0cda0835a00c23358b61dd482d5b6da94cb67c6d.jpg", "tidv2": 2154, "tnamev2": "剧情演绎", "pid_v2": 1021, "pid_name_v2": "小剧场", "bvid": "BV1uPf1BsEGX", "season_type": 0, "is_ogv": false, "ogv_info": null, "enable_vt": 0, "ai_rcmd": null, "rcmd_reason": {"content": "", "corner_mark": 0}}, {"aid": 116125799026574, "videos": 1, "tid": 21, "tname": "日常", "copyright": 1, "pic": "http://i2.hdslb.com/bfs/archive/a2dc7f58d7425c40ca8c1f5a3ab75622f7ea31be.jpg", "title": "在乌兹别克斯坦和本地富家千金约会一天是什么体验", "pubdate": 1771940025, "ctime": 1771939899, "desc": "-", "state": 0, "duration": 2092, "rights": {"bp": 0, "elec": 0, "download": 0, "movie": 0, "pay": 0, "hd5": 0, "no_reprint": 1, "autoplay": 1, "ugc_pay": 0, "is_cooperation": 0, "ugc_pay_preview": 0, "no_background": 0, "arc_pay": 0, "pay_free_watch": 0}, "owner": {"mid": 35674508, "name": "SAIsai不水视频", "face": "https://i2.hdslb.com/bfs/face/b75bc7f73911a944462badf38c6fec2db2a75183.jpg"}, "stat": {"aid": 116125799026574, "view": 245875, "danmaku": 1152, "reply": 1101, "favorite": 3189, "coin": 2186, "share": 546, "now_rank": 0, "his_rank": 0, "like": 6238, "dislike": 0, "vt": 0, "vv": 245875, "fav_g": 0, "like_g": 0}, "dynamic": "", "cid": 36259693441, "dimension": {"width": 1920, "height": 1080, "rotate": 0}, "short_link_v2": "https://b23.tv/BV1kif2BnEdB", "up_from_v2": 35, "first_frame": "http://i2.hdslb.com/bfs/storyff/_000037k22acbd169g1zikj8qcxki09b_firsti.jpg", "pub_location": "俄罗斯", "cover43": "", "tidv2": 2158, "tnamev2": "旅游记录", "pid_v2": 1022, "pid_name_v2": "旅游出行", "bvid": "BV1kif2BnEdB", "season_type": 0, "is_ogv": false, "ogv_info": null, "enable_vt": 0, "ai_rcmd": null, "rcmd_reason": {"content": "", "corner_mark": 0}}, {"aid": 116119155248945, "videos": 1, "tid": 183, "tname": "影视剪辑", "copyright": 1, "pic": "http://i2.hdslb.com/bfs/archive/41976310a16697b1c3d9badc1375834b92fe3563.jpg", "title": "震撼首发！蜘蛛侠＆死侍穿越复活格温！【B站AI创作大赛-开放赛道】", "pubdate": 1771837900, "ctime": 1771837900, "desc": "各位，拒绝意难平！如果喜欢的话 请给个一键三连！\n（注：本视频内容素材为AI生成，后期人工精修剪辑合成。版权归属电影角色IP版权方。）\n----------------------------------\n“如果那根蛛丝再快一点点……” \n这不仅是加菲虫一生的痛，更是我们所有人十几年来来最大的意难平。\n但如果，这个充满遗憾的宇宙，闯入了一个不按套路出牌的“小贱贱”呢？ 当死侍意外穿越到超凡宇宙，竟和加菲虫意外处成了“最佳损友”。在听闻了格温的悲剧后，决定替兄弟干票大的！\n强行打破宿命，把格温救回来！\n为了", "state": 0, "duration": 666, "mission_id": 4057767, "rights": {"bp": 0, "elec": 0, "download": 0, "movie": 0, "pay": 0, "hd5": 1, "no_reprint": 1, "autoplay": 1, "ugc_pay": 0, "is_cooperation": 0, "ugc_pay_preview": 0, "no_background": 0, "arc_pay": 0, "pay_free_watch": 0}, "owner": {"mid": 12098841, "name": "Nero_闪灵", "face": "https://i0.hdslb.com/bfs/face/efadc1de67a2d61b0bfc8d0784dc8587e30d516d.jpg"}, "stat": {"aid": 116119155248945, "view": 1407609, "danmaku": 3154, "reply": 3133, "favorite": 36442, "coin": 66811, "share": 14829, "now_rank": 0, "his_rank": 10, "like": 125525, "dislike": 0, "vt": 0, "vv": 1407609, "fav_g": 430, "like_g": 298}, "dynamic": "", "cid": 36231647113, "dimension": {"width": 1920, "height": 1080, "rotate": 0}, "short_link_v2": "https://b23.tv/BV1T8fqBeEz4", "first_frame": "http://i0.hdslb.com/bfs/storyff/_00003a1wrhf8fzuiq2bwhaiuc8yxjsb_firsti.jpg", "pub_location": "山东", "cover43": "http://i0.hdslb.com/bfs/archive/44a4ba60b1f45dac2d018bf9410f43e3afae1c85.jpg", "tidv2": 2006, "tnamev2": "AI影视", "pid_v2": 1001, "pid_name_v2": "影视", "bvid": "BV1T8fqBeEz4", "season_type": 0, "is_ogv": false, "ogv_info": null, "enable_vt": 0, "ai_rcmd": null, "rcmd_reason": {"content": "百万播放", "corner_mark": 1}}, {"aid": 116117729182233, "videos": 1, "tid": 17, "tname": "单机游戏", "copyright": 1, "pic": "http://i1.hdslb.com/bfs/archive/4eeda33966c0e41b3c0c9e49dd406e99f330e095.jpg", "title": "“喜 极 而 泣”", "pubdate": 1771816010, "ctime": 1771816010, "desc": "喜欢就三连支持一下吧(>^ω^<)", "state": 0, "duration": 113, "rights": {"bp": 0, "elec": 0, "download": 0, "movie": 0, "pay": 0, "hd5": 0, "no_reprint": 1, "autoplay": 1, "ugc_pay": 0, "is_cooperation": 0, "ugc_pay_preview": 0, "no_background": 0, "arc_pay": 0, "pay_free_watch": 0}, "owner": {"mid": 1042277203, "name": "星雨Starrain", "face": "https://i1.hdslb.com/bfs/face/4cacaa939a4ffe8481f79d98298851cf2d70e8f4.jpg"}, "stat": {"aid": 116117729182233, "view": 4298441, "danmaku": 3716, "reply": 4790, "favorite": 121919, "coin": 46298, "share": 2976, "now_rank": 0, "his_rank": 11, "like": 295122, "dislike": 0, "vt": 0, "vv": 4298441, "fav_g": 79668, "like_g": 59888}, "dynamic": "太痛了！！！", "cid": 36226270993, "dimension": {"width": 1920, "height": 1080, "rotate": 0}, "season_id": 1872975, "short_link_v2": "https://b23.tv/BV1YUfMBZEjQ", "up_from_v2": 36, "first_frame": "http://i1.hdslb.com/bfs/storyff/_00002ms0akfuinma02h6zskwayo1kpb_firsti.jpg", "pub_location": "四川", "cover43": "http://i1.hdslb.com/bfs/archive/a8ab3ba0ddc51fb939bb05fd896ccbea6341a142.jpg", "tidv2": 2078, "tnamev2": "沙盒类", "pid_v2": 1008, "pid_name_v2": "游戏", "bvid": "BV1YUfMBZEjQ", "season_type": 0, "is_ogv": false, "ogv_info": null, "enable_vt": 0, "ai_rcmd": null, "rcmd_reason": {"content": "百万播放", "corner_mark": 1}}, {"aid": 116119474016189, "videos": 1, "tid": 17, "tname": "单机游戏", "copyright": 1, "pic": "http://i2.hdslb.com/bfs/archive/4e1cca10e486627d23fa796cc925391712c73e19.jpg", "title": "[全网首发] 迷你世界与minecraft跨平台联机", "pubdate": 1771842763, "ctime": 1771842749, "desc": "6天14岁初中生单人完成迷你世界与minecraft跨平台联机\n\n继上次的迷你世界存档转我的世界之后，我在手机上使用 ZeroTermux 完成了对迷你世界登录协议和进服协议的逆向。这里使用了 gophertunnel 库实现基岩版协议，通过进一步的转发和翻译，进而完成了跨平台联机。但由于迷你世界与minecraft本质的不同，仍有大量功能未实现，比如说最大的问题是方块镜像，这是由于双方 x 轴定义不一样导致的。现在仅实现了方块显示、聊天框互通、移动、挖方块等功能，其他的还得等后续实现。这里还有个关于使用", "state": 0, "duration": 79, "mission_id": 4058174, "rights": {"bp": 0, "elec": 0, "download": 0, "movie": 0, "pay": 0, "hd5": 0, "no_reprint": 1, "autoplay": 1, "ugc_pay": 0, "is_cooperation": 1, "ugc_pay_preview": 0, "no_background": 0, "arc_pay": 0, "pay_free_watch": 0}, "owner": {"mid": 1378292318, "name": "是只耶吧", "face": "https://i2.hdslb.com/bfs/face/372ff363b8c439f1eafa59000b8b8d25db09c76b.jpg"}, "stat": {"aid": 116119474016189, "view": 2313212, "danmaku": 12875, "reply": 29743, "favorite": 72648, "coin": 42584, "share": 123872, "now_rank": 0, "his_rank": 5, "like": 262210, "dislike": 0, "vt": 0, "vv": 2313212, "fav_g": 69, "like_g": 29}, "dynamic": "", "cid": 36234070585, "dimension": {"width": 1280, "height": 576, "rotate": 0}, "short_link_v2": "https://b23.tv/BV1HcfqBWELq", "up_from_v2": 35, "first_frame": "http://i1.hdslb.com/bfs/storyff/_00001dk8etuqiwiyw2kmmpwr8bsdj2b_firsti.jpg", "pub_location": "广西", "cover43": "http://i1.hdslb.com/bfs/archive/f2ee157ce0ecc96bff2e6826ebd07140505f6906.jpg", "tidv2": 2103, "tnamev2": "工程机械", "pid_v2": 1012, "pid_name_v2": "科技数码", "bvid": "BV1HcfqBWELq", "season_type": 0, "is_ogv": false, "ogv_info": null, "enable_vt": 0, "ai_rcmd": null, "rcmd_reason": {"content": "百万播放", "corner_mark": 1}}, {"aid": 116119440465756, "videos": 1, "tid": 21, "tname": "日常", "copyright": 1, "pic": "http://i1.hdslb.com/bfs/archive/97846e61fade2420e56ea54e4b59d9d072dec5bd.jpg", "title": "刀锋上的不是锈，是岁月。", "pubdate": 1771843147, "ctime": 1771842209, "desc": "福利", "state": 0, "duration": 135, "rights": {"bp": 0, "elec": 0, "download": 0, "movie": 0, "pay": 0, "hd5": 1, "no_reprint": 1, "autoplay": 1, "ugc_pay": 0, "is_cooperation": 0, "ugc_pay_preview": 0, "no_background": 0, "arc_pay": 0, "pay_free_watch": 0}, "owner": {"mid": 3546772089604679, "name": "剪子没有刀", "face": "https://i2.hdslb.com/bfs/face/9c4d0918ce831d203ff1a46409602f79cf4b1d16.jpg"}, "stat": {"aid": 116119440465756, "view": 3970022, "danmaku": 2248, "reply": 12453, "favorite": 25155, "coin": 5516, "share": 3371, "now_rank": 0, "his_rank": 7, "like": 223273, "dislike": 0, "vt": 0, "vv": 3970022, "fav_g": 0, "like_g": 0}, "dynamic": "", "cid": 36233939523, "dimension": {"width": 2160, "height": 3840, "rotate": 0}, "short_link_v2": "https://b23.tv/BV1EgfqB7EgX", "up_from_v2": 9, "first_frame": "http://i0.hdslb.com/bfs/storyff/_000002n2hiut180r62shwypp7n8o12b_firsti.jpg", "pub_location": "河北", "cover43": "http://i2.hdslb.com/bfs/archive/fa8ec5bd2acd5c0afdd51281b1d6eb7fa4cfbdd2.jpg", "tidv2": 2148, "tnamev2": "其他手工", "pid_v2": 1019, "pid_name_v2": "手工", "bvid": "BV1EgfqB7EgX", "season_type": 0, "is_ogv": false, "ogv_info": null, "enable_vt": 0, "ai_rcmd": null, "rcmd_reason": {"content": "百万播放", "corner_mark": 1}}, {"aid": 116112310148911, "videos": 1, "tid": 195, "tname": "动态漫·广播剧", "copyright": 1, "pic": "http://i1.hdslb.com/bfs/archive/a3436fbcda0bb8e2bec835897be08694c5248556.jpg", "title": "碰见这种鱼到底能不能吃？看完视频就知道了。", "pubdate": 1771733386, "ctime": 1771733387, "desc": "-", "state": 0, "duration": 242, "rights": {"bp": 0, "elec": 0, "download": 0, "movie": 0, "pay": 0, "hd5": 1, "no_reprint": 1, "autoplay": 1, "ugc_pay": 0, "is_cooperation": 0, "ugc_pay_preview": 0, "no_background": 0, "arc_pay": 0, "pay_free_watch": 0}, "owner": {"mid": 1707168152, "name": "呆呆说万物", "face": "https://i2.hdslb.com/bfs/face/4b4c83f8269222927abbc69aef95c215a02badea.jpg"}, "stat": {"aid": 116112310148911, "view": 5155669, "danmaku": 37576, "reply": 2798, "favorite": 59244, "coin": 37066, "share": 1253, "now_rank": 0, "his_rank": 2, "like": 402435, "dislike": 0, "vt": 0, "vv": 5155669, "fav_g": 37350, "like_g": 30358}, "dynamic": "", "cid": 36208050236, "dimension": {"width": 1080, "height": 1920, "rotate": 0}, "short_link_v2": "https://b23.tv/BV1bCfFBFEnb", "up_from_v2": 36, "first_frame": "http://i0.hdslb.com/bfs/storyff/_00003dyanxgkz4j3t29jo2m8dhzwq1b_firsti.jpg", "pub_location": "浙江", "cover43": "", "tidv2": 2170, "tnamev2": "野生动物·动物解说科普", "pid_v2": 1024, "pid_name_v2": "动物", "bvid": "BV1bCfFBFEnb", "season_type": 0, "is_ogv": false, "ogv_info": null, "enable_vt": 0, "ai_rcmd": null, "rcmd_reason": {"content": "百万播放", "corner_mark": 1}}, {"aid": 116092211042268, "videos": 1, "tid": 256, "tname": "短片", "copyright": 1, "pic": "http://i1.hdslb.com/bfs/archive/868743bcf80e9a5673e38bf9a08ca1ff627b02e5.jpg", "title": "情绪证据【B站AI创作大赛-开放赛道】", "pubdate": 1771426795, "ctime": 1771426795, "desc": "当情绪被制度记录，\n不合时宜的冷静，\n是否也构成过错？", "state": 0, "duration": 473, "mission_id": 4057767, "rights": {"bp": 0, "elec": 0, "download": 0, "movie": 0, "pay": 0, "hd5": 1, "no_reprint": 1, "autoplay": 1, "ugc_pay": 0, "is_cooperation": 0, "ugc_pay_preview": 0, "no_background": 0, "arc_pay": 0, "pay_free_watch": 0}, "owner": {"mid": 12951481, "name": "Kkai生成影像", "face": "https://i1.hdslb.com/bfs/face/ff6c9d3453f6182bb841c031853f90594732d3c5.jpg"}, "stat": {"aid": 116092211042268, "view": 360854, "danmaku": 166, "reply": 216, "favorite": 5228, "coin": 1133, "share": 616, "now_rank": 0, "his_rank": 0, "like": 31738, "dislike": 0, "vt": 0, "vv": 360854, "fav_g": 13, "like_g": 4}, "dynamic": "", "cid": 36145727605, "dimension": {"width": 2560, "height": 1440, "rotate": 0}, "short_link_v2": "https://b23.tv/BV1w4ZRBiES6", "first_frame": "http://i0.hdslb.com/bfs/storyff/_00003i1va9o0y770p2w3u92edx9aaob_firsti.jpg", "pub_location": "意大利", "cover43": "http://i0.hdslb.com/bfs/archive/4098d3bd5f6a8271b4da2e98a9e173bce6fec96e.jpg", "tidv2": 2006, "tnamev2": "AI影视", "pid_v2": 1001, "pid_name_v2": "影视", "bvid": "BV1w4ZRBiES6", "season_type": 0, "is_ogv": false, "ogv_info": null, "enable_vt": 0, "ai_rcmd": null, "rcmd_reason": {"content": "人气飙升", "corner_mark": 1}}, {"aid": 116120749153984, "videos": 1, "tid": 17, "tname": "单机游戏", "copyright": 1, "pic": "http://i1.hdslb.com/bfs/archive/9857752456d21f05bf1c853c18233fb0da19b67a.jpg", "title": "猎哥说有人在抱哈夫币【三角洲动画】", "pubdate": 1771862475, "ctime": 1771862475, "desc": "这条视频做了很久，因为生病还是延期发布了，但是还是特别感谢所有支持我们的粉丝，也祝各位新年快乐！\n最后这是我们所有的CV老师，如果大家喜欢他们的话也可以多多关注他们\n本期的CV老师们是：\n瑶光/红翎（猎哥）-@绝音加油鸭 阳尘（金狼）/疯龙-@爱恰饭的漠桀 幻海（三套威龙）-@百里镇的屠小屠\n夏赫/疾风-@星酱biubiu  二哥红狼-@CV清觞 三弟鸟兽兽-@夏弋_\n鼠鼠蜂医/幽默无名/深蓝二号-@云中亭曲 深蓝队长-@蔚蓝星空_Star\n大狼-@一木没烦恼 小麦-@月球人雅直丶（特别鸣谢二位老师来客串", "state": 0, "duration": 1092, "rights": {"bp": 0, "elec": 0, "download": 0, "movie": 0, "pay": 0, "hd5": 1, "no_reprint": 1, "autoplay": 1, "ugc_pay": 0, "is_cooperation": 0, "ugc_pay_preview": 0, "no_background": 0, "arc_pay": 0, "pay_free_watch": 0}, "owner": {"mid": 775788, "name": "神·潜行瞬杀", "face": "https://i0.hdslb.com/bfs/face/6464b0d5ef96794d2463b2a4b054a0c91e90f3e2.jpg"}, "stat": {"aid": 116120749153984, "view": 1210039, "danmaku": 9834, "reply": 4777, "favorite": 39286, "coin": 51217, "share": 4526, "now_rank": 0, "his_rank": 19, "like": 108789, "dislike": 0, "vt": 0, "vv": 1210039, "fav_g": 9352, "like_g": 5951}, "dynamic": "", "cid": 36254191157, "dimension": {"width": 2560, "height": 1080, "rotate": 0}, "season_id": 5824730, "short_link_v2": "https://b23.tv/BV1PnfBB8EhW", "first_frame": "http://i1.hdslb.com/bfs/storyff/_000015p78ep6zmzto1yn3yt8qicv07b_firsti.jpg", "pub_location": "上海", "cover43": "http://i0.hdslb.com/bfs/archive/c6fe3a6479dd1f6ace7875561bb8eeb92200fccc.jpg", "tidv2": 2037, "tnamev2": "同人动画", "pid_v2": 1005, "pid_name_v2": "二次元", "bvid": "BV1PnfBB8EhW", "season_type": 0, "is_ogv": false, "ogv_info": null, "enable_vt": 0, "ai_rcmd": null, "rcmd_reason": {"content": "10万点赞", "corner_mark": 1}}, {"aid": 116125413150547, "videos": 1, "tid": 21, "tname": "日常", "copyright": 1, "pic": "http://i1.hdslb.com/bfs/archive/90b169da19a17b694d4964d1aa2c3f8727d570ed.jpg", "title": "我们从网上买来了各种奇怪的饮料…", "pubdate": 1771933737, "ctime": 1771933737, "desc": "", "state": 0, "duration": 2026, "mission_id": 4058108, "rights": {"bp": 0, "elec": 0, "download": 0, "movie": 0, "pay": 0, "hd5": 1, "no_reprint": 1, "autoplay": 1, "ugc_pay": 0, "is_cooperation": 0, "ugc_pay_preview": 0, "no_background": 0, "arc_pay": 0, "pay_free_watch": 0}, "owner": {"mid": 327757321, "name": "摸鱼事务所", "face": "https://i1.hdslb.com/bfs/face/93c8bd776691b3b114b5e06f5c8dff96a28f7c82.jpg"}, "stat": {"aid": 116125413150547, "view": 343895, "danmaku": 4456, "reply": 1516, "favorite": 13718, "coin": 39974, "share": 1507, "now_rank": 0, "his_rank": 0, "like": 41996, "dislike": 0, "vt": 0, "vv": 343895, "fav_g": 102, "like_g": 9}, "dynamic": "", "cid": 36257858183, "dimension": {"width": 3840, "height": 2160, "rotate": 0}, "short_link_v2": "https://b23.tv/BV13kfmBKEPn", "first_frame": "http://i0.hdslb.com/bfs/storyff/_00000bhm19okgx9pr27rvfad4i9zcob_firsti.jpg", "pub_location": "北京", "cover43": "http://i2.hdslb.com/bfs/archive/8a98f73ba9cfb3a914197fe37244872e6ab5f042.jpg", "tidv2": 2151, "tnamev2": "美食测评", "pid_v2": 1020, "pid_name_v2": "美食", "bvid": "BV13kfmBKEPn", "season_type": 0, "is_ogv": false, "ogv_info": null, "enable_vt": 0, "ai_rcmd": null, "rcmd_reason": {"content": "", "corner_mark": 0}}, {"aid": 116115715921659, "videos": 1, "tid": 21, "tname": "日常", "copyright": 1, "pic": "http://i2.hdslb.com/bfs/archive/b455f7b0e3e46b3cac017e1984223fdeb7e5152c.jpg", "title": "当大学生要开学了开始着手准备肥肥撤离时", "pubdate": 1771785678, "ctime": 1771785678, "desc": "-", "state": 0, "duration": 96, "mission_id": 4057995, "rights": {"bp": 0, "elec": 0, "download": 0, "movie": 0, "pay": 0, "hd5": 0, "no_reprint": 1, "autoplay": 1, "ugc_pay": 0, "is_cooperation": 0, "ugc_pay_preview": 0, "no_background": 0, "arc_pay": 0, "pay_free_watch": 0}, "owner": {"mid": 3546657098566166, "name": "黏豆包不嘻嘻", "face": "https://i2.hdslb.com/bfs/face/380878d9f6d29a05c0684c1aae25e740e2c7e65d.jpg"}, "stat": {"aid": 116115715921659, "view": 1419122, "danmaku": 166, "reply": 561, "favorite": 10471, "coin": 781, "share": 1123, "now_rank": 0, "his_rank": 0, "like": 109609, "dislike": 0, "vt": 0, "vv": 1419122, "fav_g": 1649, "like_g": 1120}, "dynamic": "", "cid": 36222402960, "dimension": {"width": 2160, "height": 3840, "rotate": 0}, "short_link_v2": "https://b23.tv/BV1A1fNBPEJz", "up_from_v2": 35, "first_frame": "http://i0.hdslb.com/bfs/storyff/_00002pzt8dlla1d2r2q5258y3eyb5qb_firsti.jpg", "pub_location": "山东", "cover43": "http://i1.hdslb.com/bfs/archive/c6275196ae71cdd433f946932d3e310a6b34c86d.jpg", "tidv2": 2154, "tnamev2": "剧情演绎", "pid_v2": 1021, "pid_name_v2": "小剧场", "bvid": "BV1A1fNBPEJz", "season_type": 0, "is_ogv": false, "ogv_info": null, "enable_vt": 0, "ai_rcmd": null, "rcmd_reason": {"content": "百万播放", "corner_mark": 1}}, {"aid": 116126033909722, "videos": 18, "tid": 172, "tname": "手机游戏", "copyright": 1, "pic": "http://i2.hdslb.com/bfs/archive/bca01048fa97139ecf5f2e4862626e7814055529.jpg", "title": "【矢量突破#2】巫术之夜全关卡 摆完挂机 简单好抄 核心突破/特别战线（持续更新中）", "pubdate": 1771943311, "ctime": 1771943311, "desc": "干员均专三60级带1级模组，逻各斯3级Δ模组，维什戴尔3级X模组，歌蒂3级X模组（给乌尔比安减伤回血，很重要）\n本视频为为懒人向挂机流攻略，不排斥手动开启的技能但少用，视频里大多数情况都是携带挂机技能的快速摆完的打法，少部分难打的关卡会选择简单好抄的手动打法，用一些决战技等手动技能，非低配攻略。\n\n视频里常用的干员及技能:\nps：视频绝大多数情况都是用的都是永续/点燃/强力击类的挂机技能，手动技能用的非常少，但用的手动技能基本都是可汗玩家很常用的技能，标记出来方便大家专精\n【先锋】桃金娘1（多数情况下可以", "state": 0, "duration": 2485, "rights": {"bp": 0, "elec": 0, "download": 0, "movie": 0, "pay": 0, "hd5": 0, "no_reprint": 1, "autoplay": 1, "ugc_pay": 0, "is_cooperation": 0, "ugc_pay_preview": 0, "no_background": 0, "arc_pay": 0, "pay_free_watch": 0}, "owner": {"mid": 31009079, "name": "萧然Q", "face": "https://i2.hdslb.com/bfs/face/dca58d7a5a1cd34b8bd152c0bf8784c1555dcd30.jpg"}, "stat": {"aid": 116126033909722, "view": 520757, "danmaku": 743, "reply": 830, "favorite": 3799, "coin": 5178, "share": 336, "now_rank": 0, "his_rank": 0, "like": 9467, "dislike": 0, "vt": 0, "vv": 520757, "fav_g": 0, "like_g": 0}, "dynamic": "", "cid": 36259628970, "dimension": {"width": 3840, "height": 2160, "rotate": 0}, "short_link_v2": "https://b23.tv/BV1Qnf2BhER6", "first_frame": "http://i2.hdslb.com/bfs/storyff/_00001qoqxnjntprhe2ea5d56x7o1kfb_firsti.jpg", "pub_location": "广东", "cover43": "http://i0.hdslb.com/bfs/archive/fbc645038069963bac3b66836202da4a084c168f.jpg", "tidv2": 2064, "tnamev2": "单人RPG游戏", "pid_v2": 1008, "pid_name_v2": "游戏", "bvid": "BV1Qnf2BhER6", "season_type": 0, "is_ogv": false, "ogv_info": null, "enable_vt": 0, "ai_rcmd": null, "rcmd_reason": {"content": "", "corner_mark": 0}}, {"aid": 116122393251725, "videos": 1, "tid": 138, "tname": "搞笑", "copyright": 1, "pic": "http://i2.hdslb.com/bfs/archive/f1e9fd722ce0c985fd527ae051974e338772884f.jpg", "title": "代驾之外 还有高手！？", "pubdate": 1771887459, "ctime": 1771887459, "desc": "-", "state": 0, "duration": 30, "mission_id": 4057995, "rights": {"bp": 0, "elec": 0, "download": 0, "movie": 0, "pay": 0, "hd5": 1, "no_reprint": 1, "autoplay": 1, "ugc_pay": 0, "is_cooperation": 0, "ugc_pay_preview": 0, "no_background": 0, "arc_pay": 0, "pay_free_watch": 0}, "owner": {"mid": 1244227141, "name": "穆天然-", "face": "https://i1.hdslb.com/bfs/face/c77491422dd5d532901d1979172df0763793d1b2.jpg"}, "stat": {"aid": 116122393251725, "view": 1429832, "danmaku": 96, "reply": 608, "favorite": 4343, "coin": 548, "share": 342, "now_rank": 0, "his_rank": 0, "like": 89377, "dislike": 0, "vt": 0, "vv": 1429832, "fav_g": 0, "like_g": 0}, "dynamic": "", "cid": 36243833383, "dimension": {"width": 1080, "height": 1920, "rotate": 0}, "season_id": 7415441, "short_link_v2": "https://b23.tv/BV1kbfkBzEeM", "up_from_v2": 36, "first_frame": "http://i1.hdslb.com/bfs/storyff/_000036c10fwevpdop2atzhh6axuc9pb_firsti.jpg", "pub_location": "吉林", "cover43": "http://i1.hdslb.com/bfs/archive/fd05a193a795554550e3180d433086e8f1f31b1d.jpg", "tidv2": 2154, "tnamev2": "剧情演绎", "pid_v2": 1021, "pid_name_v2": "小剧场", "bvid": "BV1kbfkBzEeM", "season_type": 0, "is_ogv": false, "ogv_info": null, "enable_vt": 0, "ai_rcmd": null, "rcmd_reason": {"content": "", "corner_mark": 0}}, {"aid": 116125530653243, "videos": 1, "tid": 172, "tname": "手机游戏", "copyright": 1, "pic": "http://i1.hdslb.com/bfs/archive/90873f7add0b957b51487e5805c622f6b26edb79.jpg", "title": "我必须全力研究这段战败CG！欢愉向解说二相乐园4.0主线！【泛式/星穹铁道】", "pubdate": 1771935309, "ctime": 1771935131, "desc": "娱乐向解说星穹铁道4.0主线剧情！这次二相乐园剧情本身就非常愉悦！\n\n录屏素材→ BV1MxcLzyEVW  by泛音1572", "state": 0, "duration": 827, "mission_id": 4061357, "rights": {"bp": 0, "elec": 0, "download": 0, "movie": 0, "pay": 0, "hd5": 0, "no_reprint": 1, "autoplay": 1, "ugc_pay": 0, "is_cooperation": 0, "ugc_pay_preview": 0, "no_background": 0, "arc_pay": 0, "pay_free_watch": 0}, "owner": {"mid": 63231, "name": "泛式", "face": "https://i0.hdslb.com/bfs/face/2608aaa45309c77ac88fbfaa40e160b8c7892985.jpg"}, "stat": {"aid": 116125530653243, "view": 454549, "danmaku": 1903, "reply": 3259, "favorite": 8047, "coin": 16805, "share": 2131, "now_rank": 0, "his_rank": 0, "like": 47127, "dislike": 0, "vt": 0, "vv": 454549, "fav_g": 3, "like_g": 1}, "dynamic": "泛式队长，突然更新！", "cid": 36258447774, "dimension": {"width": 1920, "height": 1080, "rotate": 0}, "season_id": 1413169, "short_link_v2": "https://b23.tv/BV1QcfmBPEUw", "first_frame": "http://i0.hdslb.com/bfs/storyff/_00001wp7m0tygkkbr2ky24qqedyoawb_firsti.jpg", "pub_location": "上海", "cover43": "http://i1.hdslb.com/bfs/archive/83f18f5256679e2b04e36a82b9a3636e3cf17f08.jpg", "tidv2": 2064, "tnamev2": "单人RPG游戏", "pid_v2": 1008, "pid_name_v2": "游戏", "bvid": "BV1QcfmBPEUw", "season_type": 0, "is_ogv": false, "ogv_info": null, "enable_vt": 0, "ai_rcmd": null, "rcmd_reason": {"content": "", "corner_mark": 0}}]